ycf/__init__.py
ycf/__init__.pyi
ycf/__main__.py
ycf/__main__.pyi
ycf/exceptions.py
ycf/exceptions.pyi
ycf/servers.py
ycf/servers.pyi
ycf/types.py
ycf/types.pyi
ycf/cli/__init__.py
ycf/cli/__init__.pyi
ycf/cli/managers.py
ycf/cli/managers.pyi
ycf/cli/responses.py
ycf/cli/responses.pyi
ycf/cli/settings.py
ycf/cli/settings.pyi
ycf/cli/sources/__init__.py
ycf/cli/sources/__init__.pyi
ycf/cli/sources/base.py
ycf/cli/sources/base.pyi
ycf/cli/sources/go_mod_source.py
ycf/cli/sources/go_mod_source.pyi
ycf/cli/sources/mapping.py
ycf/cli/sources/mapping.pyi
ycf/cli/sources/py_pyproject_source.py
ycf/cli/sources/py_pyproject_source.pyi
ycf/cli/sources/py_requirements_source.py
ycf/cli/sources/py_requirements_source.pyi
ycf/cli/utils/__init__.py
ycf/cli/utils/__init__.pyi
ycf/cli/utils/requirements_converter.py
ycf/cli/utils/requirements_converter.pyi
ycf/cli/yc/__init__.py
ycf/cli/yc/__init__.pyi
ycf/cli/yc/client.py
ycf/cli/yc/client.pyi
ycf/cli/yc/dto.py
ycf/cli/yc/dto.pyi
ycf_tools-0.1.9.dist-info/METADATA
ycf_tools-0.1.9.dist-info/WHEEL
ycf_tools-0.1.9.dist-info/entry_points.txt
ycf_tools-0.1.9.dist-info/licenses/LICENSE
ycf_tools-0.1.9.dist-info/RECORD
