Metadata-Version: 2.4
Name: ycf-tools
Version: 0.1.9
Summary: Yandex Cloud Function tools
Author-email: Aleksei Marusich <aleksei.marusich@rocshers.com>
License: MIT
License-File: LICENSE
Keywords: cloud,function,rocshers,yandex
Classifier: Intended Audience :: Developers
Classifier: Intended Audience :: Information Technology
Classifier: License :: OSI Approved :: MIT License
Classifier: Programming Language :: Python
Classifier: Programming Language :: Python :: 3
Classifier: Programming Language :: Python :: 3 :: Only
Classifier: Programming Language :: Python :: 3.12
Classifier: Topic :: Software Development :: Libraries
Classifier: Topic :: Software Development :: Libraries :: Python Modules
Classifier: Topic :: System :: Software Distribution
Requires-Python: >=3.12
Requires-Dist: pydantic>=2
Provides-Extra: cli
Requires-Dist: boto3>=1.36.16; extra == 'cli'
Requires-Dist: clickpy-client>=0.1.5; extra == 'cli'
Requires-Dist: cryptography>=44.0.1; extra == 'cli'
Requires-Dist: httpx>=0.28.1; extra == 'cli'
Requires-Dist: package-schemes==0.1.2; extra == 'cli'
Requires-Dist: packaging-version-git>=0.1.2; extra == 'cli'
Requires-Dist: pydantic-settings>=2; extra == 'cli'
Requires-Dist: pyjwt>=2.10.1; extra == 'cli'
Requires-Dist: rich>=13.9.3; extra == 'cli'
Requires-Dist: typer>=0.12.5; extra == 'cli'
